LICENSE
MANIFEST.in
README.md
pom.xml
setup.cfg
setup.py
src/motuclient/motuclient.py
src/motuclient.egg-info/PKG-INFO
src/motuclient.egg-info/SOURCES.txt
src/motuclient.egg-info/dependency_links.txt
src/motuclient.egg-info/entry_points.txt
src/motuclient.egg-info/requires.txt
src/motuclient.egg-info/top_level.txt
src/motuclient/motu_utils/__init__.py
src/motuclient/motu_utils/motu_api.py
src/motuclient/motu_utils/stop_watch.py
src/motuclient/motu_utils/utils_cas.py
src/motuclient/motu_utils/utils_collection.py
src/motuclient/motu_utils/utils_configpath.py
src/motuclient/motu_utils/utils_html.py
src/motuclient/motu_utils/utils_http.py
src/motuclient/motu_utils/utils_log.py
src/motuclient/motu_utils/utils_messages.py
src/motuclient/motu_utils/utils_stream.py
src/motuclient/motu_utils/utils_unit.py
src/motuclient/motu_utils/cfg/log.ini
src/motuclient/motu_utils/cfg/messages.properties