Metadata-Version: 1.2
Name: motuclient
Version: 3.0.0
Summary: Extract and download gridded data through a python command line from Motu web server. Used in CMEMS context http://marine.copernicus.eu/
Home-page: https://github.com/clstoulouse/motu-client-python
Author: Sylvain MARTY, CLS
Author-email: smarty@groupcls.com
License: LGPL
Download-URL: https://github.com/clstoulouse/motu-client-python/releases/
Keywords: Copernicus,CMEMS,CLS,Motu,motuclient-python,Dissemination Unit
Platform: any
Classifier: Development Status :: 5 - Production/Stable
Classifier: Programming Language :: Python :: 3.7
Classifier: License :: OSI Approved :: GNU Lesser General Public License v3 (LGPLv3)
Classifier: Topic :: Scientific/Engineering :: GIS
Classifier: Environment :: Console
Classifier: Natural Language :: English
Classifier: Operating System :: OS Independent
Requires-Python: >=2.7
